egger/__init__.py
egger/__main__.py
egger/main.py
egger/compare/__init__.py
egger/compare/barchart.py
egger/compare/compare.py
egger/compare/rank.py
egger/parser/__init__.py
egger/parser/compare.py
egger/parser/parser.py
egger/parser/window.py
egger/utils/__init__.py
egger/utils/errors.py
egger/utils/io.py
egger/utils/process.py
egger/window/__init__.py
egger/window/slide.py
egger/window/window.py
egger-1.0.1.dist-info/LICENSE
egger-1.0.1.dist-info/METADATA
egger-1.0.1.dist-info/WHEEL
egger-1.0.1.dist-info/entry_points.txt
egger-1.0.1.dist-info/top_level.txt
egger-1.0.1.dist-info/RECORD
