Metadata-Version: 2.2
Name: egger
Version: 1.0.1
Summary: a python package for graphing emapper results
Home-page: https://github.com/DrBoothTJ/egger
Author: Thomas J. Booth
Author-email: thoboo@biosustain.dtu.dk
License: GNU General Public License v3.0
Requires-Python: >=3.9
License-File: LICENSE
Requires-Dist: matplotlib
Requires-Dist: plotly
Requires-Dist: scipy
Requires-Dist: seaborn
Requires-Dist: Bio
Dynamic: author
Dynamic: author-email
Dynamic: description
Dynamic: description-content-type
Dynamic: home-page
Dynamic: license
Dynamic: requires-dist
Dynamic: requires-python
Dynamic: summary
